efck/__init__.py
efck/__main__.py
efck/_version.py
efck/config.py
efck/emoji-custom-strings.txt
efck/emoji-ordering.txt
efck/emoji-shortcodes.txt
efck/emoji.py
efck/gui.py
efck/output.py
efck/qt.py
efck/tab.py
efck/tests.py
efck/util.py
efck/_qt/pyqt5.py
efck/_qt/pyqt6.py
efck/_qt/pyside6.py
efck/_qt/qtpy.py
efck/filters/README.md
efck/filters/bold.py
efck/filters/chemical.py
efck/filters/cursive.py
efck/filters/emphasized.py
efck/filters/gothic.py
efck/filters/leetspeak.py
efck/filters/lmgtfy.py
efck/filters/monospace.py
efck/filters/rounded.py
efck/filters/squared.py
efck/filters/striked.py
efck/filters/strikethrough.py
efck/filters/underline.py
efck/filters/upside_down.py
efck/filters/zalgo.py
efck/icons/PB_tenor_logo_blue_vertical.png
efck/icons/Poweredby_100px-White_VertLogo.png
efck/icons/awesome-emoji.png
efck/icons/gears.png
efck/icons/gifs.png
efck/icons/logo.png
efck/icons/strikethrough.png
efck/tabs/__init__.py
efck/tabs/_options.py
efck/tabs/emoji.py
efck/tabs/filters.py
efck/tabs/gifs.py
efck-1.2.dist-info/licenses/LICENSE.txt
efck-1.2.dist-info/METADATA
efck-1.2.dist-info/WHEEL
efck-1.2.dist-info/entry_points.txt
efck-1.2.dist-info/top_level.txt
efck-1.2.dist-info/RECORD
