Metadata-Version: 2.4
Name: efck
Version: 1.2
Summary: Emoji filter / Unicode chat keyboard
Home-page: https://efck-chat-keyboard.github.io/
Author: Nono Viamoto
License: AGPL-3.0
Project-URL: Source, https://github.com/efck-chat-keyboard/efck
Project-URL: Tracker, https://github.com/efck-chat-keyboard/efck/issues
Classifier: Development Status :: 5 - Production/Stable
Classifier: Environment :: MacOS X
Classifier: Environment :: Win32 (MS Windows)
Classifier: Environment :: X11 Applications :: Qt
Classifier: Intended Audience :: Customer Service
Classifier: Intended Audience :: End Users/Desktop
Classifier: License :: OSI Approved :: GNU Affero General Public License v3 or later (AGPLv3+)
Classifier: Operating System :: MacOS
Classifier: Operating System :: Microsoft :: Windows
Classifier: Operating System :: POSIX :: Linux
Classifier: Operating System :: OS Independent
Classifier: Programming Language :: Python :: 3 :: Only
Classifier: Topic :: Adaptive Technologies
Classifier: Topic :: Communications :: Chat
Classifier: Topic :: Communications :: Email
Classifier: Topic :: Text Processing :: Filters
Requires-Python: >=3.7
License-File: LICENSE.txt
Provides-Extra: doc
Provides-Extra: dev
Requires-Dist: flake8; extra == "dev"
Requires-Dist: coverage; extra == "dev"
Requires-Dist: pyinstaller; extra == "dev"
Requires-Dist: pillow; extra == "dev"
Provides-Extra: extra
Requires-Dist: unicodedata2; extra == "extra"
Dynamic: author
Dynamic: classifier
Dynamic: description
Dynamic: description-content-type
Dynamic: home-page
Dynamic: license
Dynamic: license-file
Dynamic: project-url
Dynamic: provides-extra
Dynamic: requires-python
Dynamic: summary
